[
  {
    "match_id": "c76b0d06-84c0-4ce7-b98b-b3a1f0f2f2e7",
    "hunter": "9313",
    "bounty": "4063",
    "hunter_time": 221,
    "bounty_time": 592,
    "winner_is_hunter": 1
  },
  {
    "match_id": "79855102-3762-4125-94e8-af65f1e5f8fc",
    "hunter": "9313",
    "bounty": "7615",
    "hunter_time": 370,
    "bounty_time": 657,
    "winner_is_hunter": 1
  },
  {
    "match_id": "78e3ebbf-978a-48a1-8fcc-3b4150521b0a",
    "hunter": "9313",
    "bounty": "9637",
    "hunter_time": 0,
    "bounty_time": 309,
    "winner_is_hunter": 1
  },
  {
    "match_id": "b77ac9af-e740-430f-8690-8bedc3f2bf70",
    "hunter": "9313",
    "bounty": "7580",
    "hunter_time": 231,
    "bounty_time": 1171,
    "winner_is_hunter": 1
  }
]